network_manager_provider/__init__.py
network_manager_provider/_version.py
network_manager_provider/codes.py
network_manager_provider/defaults.py
network_manager_provider/address/__init__.py
network_manager_provider/address/assign.py
network_manager_provider/address/delete.py
network_manager_provider/address/read.py
network_manager_provider/bundle/__init__.py
network_manager_provider/bundle/apply.py
network_manager_provider/bundle/config.py
network_manager_provider/bundle/create.py
network_manager_provider/bundle/delete.py
network_manager_provider/bundle/flush.py
network_manager_provider/bundle/ls.py
network_manager_provider/bundle/read.py
network_manager_provider/bundle/undo.py
network_manager_provider/bundle/update.py
network_manager_provider/cli/__init__.py
network_manager_provider/cli/cli.py
network_manager_provider/cli/corc.py
network_manager_provider/cli/helpers.py
network_manager_provider/cli/input_groups/__init__.py
network_manager_provider/cli/input_groups/address.py
network_manager_provider/cli/input_groups/bundle.py
network_manager_provider/cli/input_groups/interface.py
network_manager_provider/cli/input_groups/namespace.py
network_manager_provider/cli/input_groups/route.py
network_manager_provider/cli/parsers/__init__.py
network_manager_provider/cli/parsers/actions.py
network_manager_provider/cli/parsers/address.py
network_manager_provider/cli/parsers/bundle.py
network_manager_provider/cli/parsers/interface.py
network_manager_provider/cli/parsers/namespace.py
network_manager_provider/cli/parsers/route.py
network_manager_provider/helpers/__init__.py
network_manager_provider/helpers/pyroute2.py
network_manager_provider/interface/__init__.py
network_manager_provider/interface/create.py
network_manager_provider/interface/delete.py
network_manager_provider/interface/flush.py
network_manager_provider/interface/ls.py
network_manager_provider/interface/read.py
network_manager_provider/interface/update.py
network_manager_provider/namespace/__init__.py
network_manager_provider-0.0.1a2.dist-info/licenses/LICENSE
network_manager_provider-0.0.1a2.dist-info/METADATA
network_manager_provider-0.0.1a2.dist-info/WHEEL
network_manager_provider-0.0.1a2.dist-info/entry_points.txt
network_manager_provider-0.0.1a2.dist-info/top_level.txt
network_manager_provider-0.0.1a2.dist-info/RECORD
