Metadata-Version: 2.4
Name: network_manager_provider
Version: 0.0.1a2
Summary: A corc plugin for providing network infrastructure
Home-page: https://github.com/rasmunk/network_manager_provider
Author: Rasmus Munk
Author-email: code@munk0.dk
License: GNU General Public License v2 (GPLv2)
Keywords: Orchstration,Networking
Classifier: Intended Audience :: Developers
Classifier: Intended Audience :: System Administrators
Classifier: Programming Language :: Python
Classifier: Programming Language :: Python :: 3.9
Classifier: Programming Language :: Python :: 3.10
Classifier: Programming Language :: Python :: 3.11
Classifier: Programming Language :: Python :: 3.12
Classifier: Programming Language :: Python :: 3.13
License-File: LICENSE
Requires-Dist: pyroute2
Requires-Dist: PyYAML>=5.4
Requires-Dist: jinja2>=3.1.3
Provides-Extra: test
Requires-Dist: pytest>=7.2.1; extra == "test"
Requires-Dist: rstcheck==6.2.4; extra == "test"
Provides-Extra: dev
Requires-Dist: flake8==6.1.0; extra == "dev"
Requires-Dist: black==24.3.0; extra == "dev"
Requires-Dist: rstcheck==6.2.4; extra == "dev"
Dynamic: author
Dynamic: author-email
Dynamic: classifier
Dynamic: description
Dynamic: description-content-type
Dynamic: home-page
Dynamic: keywords
Dynamic: license
Dynamic: license-file
Dynamic: provides-extra
Dynamic: requires-dist
Dynamic: summary
